diophantine.py
Diophantine-0.2.0.dist-info/DESCRIPTION.rst
Diophantine-0.2.0.dist-info/METADATA
Diophantine-0.2.0.dist-info/RECORD
Diophantine-0.2.0.dist-info/WHEEL
Diophantine-0.2.0.dist-info/metadata.json
Diophantine-0.2.0.dist-info/top_level.txt
