Metadata-Version: 2.0
Name: Diophantine
Version: 0.2.0
Summary: A python package for finding small solutions of systems of diophantine (integer algebra) equations
Home-page: UNKNOWN
Author: Thomas G. Close
Author-email: tom.g.close@gmail.com
License: MIT
Keywords: mathematics,diophantine,algebra,integer,systems
Platform: UNKNOWN
Classifier: Development Status :: 4 - Beta
Classifier: Environment :: Console
Classifier: Intended Audience :: Science/Research
Classifier: License :: OSI Approved :: MIT License
Classifier: Natural Language :: English
Classifier: Operating System :: OS Independent
Classifier: Programming Language :: Python :: 2
Classifier: Programming Language :: Python :: 2.7
Classifier: Programming Language :: Python :: 3
Classifier: Programming Language :: Python :: 3.4
Classifier: Programming Language :: Python :: 3.5
Classifier: Programming Language :: Python :: 3.6
Classifier: Topic :: Scientific/Engineering
Requires-Python: >=2.7, !=3.0.*, !=3.1.*, !=3.2.*, !=3.3.*, <4
Requires-Dist: sympy (>=1.1)
Requires-Dist: future (>=0.16)
